spotipy/__init__.py
spotipy/cache_handler.py
spotipy/client.py
spotipy/exceptions.py
spotipy/oauth2.py
spotipy/util.py
spotipy-2.24.0.dist-info/LICENSE.md
spotipy-2.24.0.dist-info/METADATA
spotipy-2.24.0.dist-info/WHEEL
spotipy-2.24.0.dist-info/top_level.txt
spotipy-2.24.0.dist-info/RECORD
