Metadata-Version: 2.1
Name: spotipy
Version: 2.24.0
Summary: A light weight Python library for the Spotify Web API
Home-page: https://spotipy.readthedocs.org/
Author: @plamere
Author-email: paul@echonest.com
License: MIT
Project-URL: Source, https://github.com/plamere/spotipy
Requires-Python: >3.8
License-File: LICENSE.md
Requires-Dist: redis>=3.5.3
Requires-Dist: requests>=2.25.0
Requires-Dist: urllib3>=1.26.0
Provides-Extra: test
Requires-Dist: mock==2.0.0; extra == "test"
Provides-Extra: memcache
Requires-Dist: pymemcache>=3.5.2; extra == "memcache"
